numapi/__init__.py
numapi/__main__.py
numapi/numapi_command_line.py
numapi/token.txt
funapis-0.4.dist-info/METADATA
funapis-0.4.dist-info/WHEEL
funapis-0.4.dist-info/entry_points.txt
funapis-0.4.dist-info/top_level.txt
funapis-0.4.dist-info/RECORD
