Metadata-Version: 2.1
Name: funapis
Version: 0.4
Summary: Command line tool for some fun api usage
Home-page: https://github.com/nirabhratapaswi/funapis
Author: Nirabhra Tapaswi
Author-email: nirabhratapaswi@gmail.com
License: UNKNOWN
Platform: UNKNOWN
Classifier: Programming Language :: Python :: 3
Classifier: License :: OSI Approved :: MIT License
Classifier: Operating System :: OS Independent
Requires-Dist: requests
